{"frames": [

{
	"filename": "baner",
	"frame": {"x":543,"y":319,"w":540,"h":177},
	"rotated": false,
	"trimmed": false,
	"spriteSourceSize": {"x":0,"y":0,"w":540,"h":177},
	"sourceSize": {"w":540,"h":177},
	"pivot": {"x":0.5,"y":0.5}
},
{
	"filename": "retro-face",
	"frame": {"x":789,"y":149,"w":332,"h":80},
	"rotated": false,
	"trimmed": false,
	"spriteSourceSize": {"x":0,"y":0,"w":332,"h":80},
	"sourceSize": {"w":332,"h":80},
	"pivot": {"x":0.5,"y":0.5}
},
{
	"filename": "retro-fondo",
	"frame": {"x":1,"y":1,"w":540,"h":480},
	"rotated": false,
	"trimmed": false,
	"spriteSourceSize": {"x":0,"y":0,"w":540,"h":480},
	"sourceSize": {"w":540,"h":480},
	"pivot": {"x":0.5,"y":0.5}
},
{
	"filename": "retro-medalla",
	"frame": {"x":543,"y":1,"w":244,"h":316},
	"rotated": false,
	"trimmed": false,
	"spriteSourceSize": {"x":0,"y":0,"w":244,"h":316},
	"sourceSize": {"w":244,"h":316},
	"pivot": {"x":0.5,"y":0.5}
},
{
	"filename": "retro-nivel",
	"frame": {"x":789,"y":1,"w":510,"h":146},
	"rotated": false,
	"trimmed": false,
	"spriteSourceSize": {"x":0,"y":0,"w":510,"h":146},
	"sourceSize": {"w":510,"h":146},
	"pivot": {"x":0.5,"y":0.5}
},
{
	"filename": "retro-reintentar",
	"frame": {"x":789,"y":231,"w":332,"h":80},
	"rotated": false,
	"trimmed": false,
	"spriteSourceSize": {"x":0,"y":0,"w":332,"h":80},
	"sourceSize": {"w":332,"h":80},
	"pivot": {"x":0.5,"y":0.5}
}],
"meta": {
	"app": "http://www.codeandweb.com/texturepacker",
	"version": "1.0",
	"image": "atlas.png",
	"format": "RGBA8888",
	"size": {"w":1300,"h":497},
	"scale": "1",
	"smartupdate": "$TexturePacker:SmartUpdate:e295a034eb30418f8e2fd1f805103616:8cc877a69bb03e093f62afbc8efca46b:cbce6b53f0f49e0bf15173c25c41f876$"
}
}
