{
"skeleton": { "hash": "/q180K/gTOSVwKi9aJHod3tf8kg", "spine": "2.1.27", "width": 101, "height": 85, "images": "" },
"bones": [
	{ "name": "root" },
	{ "name": "figure", "parent": "root", "length": 61.24, "x": -0.01, "y": 0.07, "rotation": 90 },
	{ "name": "face", "parent": "figure", "x": 50.57, "inheritScale": false }
],
"slots": [
	{ "name": "figure", "bone": "figure", "attachment": "cube" },
	{ "name": "face", "bone": "face", "attachment": "face1" }
],
"skins": {
	"default": {},
	"circle": {
		"face": {
			"face1": { "name": "normal/face1", "y": -0.01, "rotation": -90, "width": 62, "height": 42 },
			"face2": { "name": "normal/face2", "y": -0.01, "rotation": -90, "width": 62, "height": 39 },
			"face3": { "name": "normal/face3", "y": -0.01, "rotation": -90, "width": 62, "height": 21 },
			"face4": { "name": "normal/face4", "y": -0.01, "rotation": -90, "width": 62, "height": 39 }
		},
		"figure": {
			"cube": { "name": "normal/circle", "x": 44.61, "y": 0.99, "rotation": -90, "width": 90, "height": 90 }
		}
	},
	"cube": {
		"face": {
			"face1": { "name": "normal/face1", "y": -0.01, "rotation": -90, "width": 62, "height": 42 },
			"face2": { "name": "normal/face2", "y": -0.01, "rotation": -90, "width": 62, "height": 39 },
			"face3": { "name": "normal/face3", "y": -0.01, "rotation": -90, "width": 62, "height": 21 },
			"face4": { "name": "normal/face4", "y": -0.01, "rotation": -90, "width": 62, "height": 39 }
		},
		"figure": {
			"cube": { "name": "normal/cube", "x": 44.61, "y": -0.01, "rotation": -90, "width": 90, "height": 90 }
		}
	},
	"rectangle": {
		"face": {
			"face1": { "name": "normal/face1", "y": -0.01, "rotation": -90, "width": 62, "height": 42 },
			"face2": { "name": "normal/face2", "y": -0.01, "rotation": -90, "width": 62, "height": 39 },
			"face3": { "name": "normal/face3", "y": -0.01, "rotation": -90, "width": 62, "height": 21 },
			"face4": { "name": "normal/face4", "y": -0.01, "rotation": -90, "width": 62, "height": 39 }
		},
		"figure": {
			"cube": { "name": "normal/rectangle", "x": 30.97, "y": 0.99, "rotation": -90, "width": 93, "height": 60 }
		}
	},
	"triangle": {
		"face": {
			"face1": { "name": "normal/face1", "y": -0.01, "rotation": -90, "width": 62, "height": 42 },
			"face2": { "name": "normal/face2", "y": -0.01, "rotation": -90, "width": 62, "height": 39 },
			"face3": { "name": "normal/face3", "y": -0.01, "rotation": -90, "width": 62, "height": 21 },
			"face4": { "name": "normal/face4", "y": -0.01, "rotation": -90, "width": 62, "height": 39 }
		},
		"figure": {
			"cube": { "name": "normal/tringule", "x": 42.59, "y": -0.01, "rotation": -90, "width": 101, "height": 85 }
		}
	}
},
"animations": {
	"IDLE": {
		"slots": {
			"face": {
				"attachment": [
					{ "time": 0, "name": "face1" },
					{ "time": 0.4333, "name": "face3" },
					{ "time": 0.6, "name": "face1" },
					{ "time": 2, "name": "face1" }
				]
			},
			"figure": {
				"attachment": [
					{ "time": 0, "name": "cube" },
					{ "time": 2, "name": "cube" }
				]
			}
		},
		"bones": {
			"figure": {
				"rotate": [
					{ "time": 0, "angle": 0 }
				],
				"translate": [
					{ "time": 0, "x": 0, "y": 0 }
				],
				"scale": [
					{
						"time": 0,
						"x": 1,
						"y": 1,
						"curve": [ 0.456, -0.5, 0.824, 1 ]
					},
					{
						"time": 0.5,
						"x": 0.832,
						"y": 1.021,
						"curve": [ 0.456, -0.5, 0.824, 1 ]
					},
					{
						"time": 1,
						"x": 1,
						"y": 1,
						"curve": [ 0.456, -0.5, 0.824, 1 ]
					},
					{
						"time": 1.4666,
						"x": 0.832,
						"y": 1.021,
						"curve": [ 0.456, -0.5, 0.824, 1 ]
					},
					{ "time": 2, "x": 1, "y": 1 }
				]
			},
			"face": {
				"rotate": [
					{ "time": 0, "angle": 0 }
				],
				"translate": [
					{
						"time": 0,
						"x": 0,
						"y": 0,
						"curve": [ 0.407, -0.71, 0.833, 1 ]
					},
					{
						"time": 0.5333,
						"x": -2.6,
						"y": 0,
						"curve": [ 0.407, -0.71, 0.833, 1 ]
					},
					{
						"time": 1.0333,
						"x": 0,
						"y": 0,
						"curve": [ 0.407, -0.71, 0.833, 1 ]
					},
					{
						"time": 1.5,
						"x": -2.6,
						"y": 0,
						"curve": [ 0.407, -0.71, 0.833, 1 ]
					},
					{ "time": 2, "x": 0, "y": 0 }
				],
				"scale": [
					{
						"time": 0,
						"x": 1,
						"y": 1,
						"curve": [ 0.114, 0, 0.641, 1.64 ]
					},
					{
						"time": 0.5333,
						"x": 0.934,
						"y": 1,
						"curve": [ 0.114, 0, 0.641, 1.64 ]
					},
					{
						"time": 1.0333,
						"x": 1,
						"y": 1,
						"curve": [ 0.114, 0, 0.641, 1.64 ]
					},
					{
						"time": 1.5,
						"x": 0.934,
						"y": 1,
						"curve": [ 0.114, 0, 0.641, 1.64 ]
					},
					{ "time": 2, "x": 1, "y": 1 }
				]
			}
		},
		"drawOrder": [
			{ "time": 0 },
			{ "time": 2 }
		]
	},
	"LOSE": {
		"slots": {
			"face": {
				"attachment": [
					{ "time": 0, "name": "face4" },
					{ "time": 0.7, "name": "face4" },
					{ "time": 1.1666, "name": "face4" }
				]
			},
			"figure": {
				"attachment": [
					{ "time": 0, "name": "cube" },
					{ "time": 1.1666, "name": "cube" }
				]
			}
		},
		"bones": {
			"face": {
				"rotate": [
					{ "time": 0, "angle": 0 }
				],
				"translate": [
					{
						"time": 0,
						"x": 0,
						"y": 0,
						"curve": [ 0.407, -0.71, 0.833, 1 ]
					},
					{
						"time": 0.6333,
						"x": -5.68,
						"y": 0,
						"curve": [ 0.407, -0.71, 0.833, 1 ]
					},
					{ "time": 1.1666, "x": 0, "y": 0 }
				],
				"scale": [
					{
						"time": 0,
						"x": 1,
						"y": 1,
						"curve": [ 0.114, 0, 0.641, 1.64 ]
					},
					{
						"time": 0.6333,
						"x": 0.934,
						"y": 1,
						"curve": [ 0.114, 0, 0.641, 1.64 ]
					},
					{ "time": 1.1666, "x": 1, "y": 1 }
				]
			},
			"figure": {
				"rotate": [
					{ "time": 0, "angle": 0 }
				],
				"translate": [
					{ "time": 0, "x": 0, "y": 0 }
				],
				"scale": [
					{
						"time": 0,
						"x": 1,
						"y": 1,
						"curve": [ 0.456, -0.5, 0.824, 1 ]
					},
					{
						"time": 0.5666,
						"x": 0.832,
						"y": 1.021,
						"curve": [ 0.456, -0.5, 0.824, 1 ]
					},
					{ "time": 1.1333, "x": 1, "y": 1 }
				]
			}
		},
		"drawOrder": [
			{ "time": 0 },
			{ "time": 1.1666 }
		]
	}
}
}